EMOC.cpython-39-darwin.so
emoc_cpp-0.0.1a1.dist-info/LICENSE.txt
emoc_cpp-0.0.1a1.dist-info/METADATA
emoc_cpp-0.0.1a1.dist-info/WHEEL
emoc_cpp-0.0.1a1.dist-info/top_level.txt
emoc_cpp-0.0.1a1.dist-info/RECORD
